multiscalemnist/__init__.py
multiscalemnist/cli.py
multiscalemnist/config.py
multiscalemnist/generate.py
multiscalemnist/mnist.py
multiscalemnist-0.8.0.dist-info/entry_points.txt
multiscalemnist-0.8.0.dist-info/WHEEL
multiscalemnist-0.8.0.dist-info/METADATA
multiscalemnist-0.8.0.dist-info/RECORD
