Metadata-Version: 2.1
Name: multiscalemnist
Version: 0.8.0
Summary: MNIST dataset for detection with multiple scales
Author: PiotrJZielinski
Author-email: piotrekzie100@gmail.com
Requires-Python: >=3.8,<4.0
Classifier: Programming Language :: Python :: 3
Classifier: Programming Language :: Python :: 3.8
Classifier: Programming Language :: Python :: 3.9
Requires-Dist: click (>=7.1.2,<8.0.0)
Requires-Dist: h5py (>=2.10.0,<3.0.0)
Requires-Dist: numpy (>=1.18.4,<2.0.0)
Requires-Dist: opencv-python (>=4.2.0,<5.0.0)
Requires-Dist: tqdm (>=4.46.0,<5.0.0)
Requires-Dist: yacs (>=0.1.7,<0.2.0)
